{
    // See https://go.microsoft.com//fwlink//?linkid=834763 for more information about this file.
    "configurations": [
        {
        "name": "Debug (x64)",
        "generator": "Ninja",
        "configurationType" : "Debug",
        "inheritEnvironments": [ "msvc_x64" ],
        "buildRoot":  "${env.USERPROFILE}\\CMakeBuilds\\${workspaceHash}\\build\\${name}",
        "cmakeCommandArgs":  "",
        "buildCommandArgs": "-v",
        "ctestCommandArgs":  ""
        },
        {
        "name": "Release (x64)",
        "generator": "Ninja",
        "configurationType" : "RelWithDebInfo",
       "inheritEnvironments": [ "msvc_x64" ],
        "buildRoot":  "${env.USERPROFILE}\\CMakeBuilds\\${workspaceHash}\\build\\${name}",
        "cmakeCommandArgs":  "",
        "buildCommandArgs": "-v",
        "ctestCommandArgs":  ""
        }
    ]
}